setup.cfg
setup.py
telegram_usernames_checker/__init__.py
telegram_usernames_checker/telegram_usernames_checker.py
telegram_usernames_checker.egg-info/PKG-INFO
telegram_usernames_checker.egg-info/SOURCES.txt
telegram_usernames_checker.egg-info/dependency_links.txt
telegram_usernames_checker.egg-info/not-zip-safe
telegram_usernames_checker.egg-info/top_level.txt