Metadata-Version: 2.1
Name: telegram-usernames-checker
Version: 0.1
Summary: Quick check of a huge number of usernames for availability in Telegram
Home-page: UNKNOWN
Author-email: beeeirym@gmail.com
License: UNKNOWN
Platform: UNKNOWN
